lndb_cli/__init__.py
lndb_cli/_core.py
lndb_cli-0.0.1.dist-info/LICENSE
lndb_cli-0.0.1.dist-info/WHEEL
lndb_cli-0.0.1.dist-info/METADATA
lndb_cli-0.0.1.dist-info/RECORD
